datastore_package/__init__.py
datastore_package/datastore.py
datastore_package-0.1.0.dist-info/METADATA
datastore_package-0.1.0.dist-info/WHEEL
datastore_package-0.1.0.dist-info/top_level.txt
datastore_package-0.1.0.dist-info/RECORD
